[
      {
        "number": 1,
        "question": "في أي سنة هجرية توجه جيش قريش إلى المدينة المنورة لمحاربة المسلمين والانتقام لهزيمتهم في بدر؟",
        "choices": [
          "السنة الثانية للهجرة",
          "السنة الثالثة للهجرة",
          "السنة الرابعة للهجرة",
          "السنة الخامسة للهجرة"
        ],
        "correct_symbol": "ب",
        "correct_answer": "السنة الثالثة للهجرة",
        "page": "81",
        "source_text": "توجه جيش قريش إلى المدينة المنورة في السنة الثالثة للهجرة، بهدف محاربة المسلمين والانتقام لهزيمتهم في بدر. خرج النبي صلى الله عليه وسلم مع مئات من الصحابة الكرام لملاقاتهم في أُحُد."
      },
      {
        "number": 2,
        "question": "أين التقى جيش المسلمين بجيش المشركين في معركة أُحُد؟",
        "choices": [
          "قرب المدينة المنورة",
          "في بدر",
          "في مكة المكرمة",
          "في حَمْراء الأسد"
        ],
        "correct_symbol": "أ",
        "correct_answer": "قرب المدينة المنورة",
        "page": "81",
        "source_text": "توجه جيش قريش إلى المدينة المنورة في السنة الثالثة للهجرة، فخرج النبي صلى الله عليه وسلم مع مئات من الصحابة الكرام، والتقى بالمشركين في أُحُد قرب المدينة المنورة."
      },
      {
        "number": 3,
        "question": "كم عدد الرماة الذين أمرهم النبي صلى الله عليه وسلم بالوقوف على جبل الرماة يوم أُحُد؟",
        "choices": [
          "ثلاثين",
          "أربعين",
          "خمسين",
          "ستين"
        ],
        "correct_symbol": "ج",
        "correct_answer": "خمسين",
        "page": "81",
        "source_text": "أمر سيدنا رسول الله صلى الله عليه وسلم خمسين من الرماة بالوقوف على جبل الرماة لحماية ظهر المسلمين، وطلب منهم ألا يتركوا مواقعهم بصرف النظر عن نتيجة المعركة."
      },
      {
        "number": 4,
        "question": "من هو الصحابي الذي قاد الرماة الخمسين على جبل الرماة يوم أُحُد؟",
        "choices": [
          "سيدنا حمزة بن عبد المطلب",
          "أنس بن النضر",
          "عبد الله بن جبير",
          "سعد بن معاذ"
        ],
        "correct_symbol": "ج",
        "correct_answer": "عبد الله بن جبير",
        "page": "81",
        "source_text": "أمر سيدنا رسول الله صلى الله عليه وسلم خمسين من الرماة بقيادة عبد الله بن جبير بالوقوف على جبل الرماة لحماية ظهر المسلمين، وطلب منهم ألا يتركوا مواقعهم."
      },
      {
        "number": 5,
        "question": "ما هي المهمة التي كلف بها النبي صلى الله عليه وسلم الرماة على جبل الرماة يوم أُحُد؟",
        "choices": [
          "مهاجمة جيش المشركين من الأمام",
          "حماية ظهر المسلمين",
          "جمع الغنائم بعد المعركة",
          "الاستطلاع وجمع المعلومات"
        ],
        "correct_symbol": "ب",
        "correct_answer": "حماية ظهر المسلمين",
        "page": "81",
        "source_text": "أمر سيدنا رسول الله صلى الله عليه وسلم خمسين من الرماة بقيادة عبد الله بن جبير بالوقوف على جبل الرماة لحماية ظهر المسلمين، وطلب منهم ألا يتركوا مواقعهم بصرف النظر عن نتيجة المعركة."
      },
      {
        "number": 6,
        "question": "ما هو الشرط الذي وضعه النبي صلى الله عليه وسلم للرماة على جبل الرماة؟",
        "choices": [
          "النزول لجمع الغنائم فور النصر",
          "البقاء في مواقعهم مهما كانت نتيجة المعركة",
          "الانسحاب إذا زاد عدد المشركين",
          "التقدم لملاحقة المشركين المنهزمين"
        ],
        "correct_symbol": "ب",
        "correct_answer": "البقاء في مواقعهم مهما كانت نتيجة المعركة",
        "page": "81",
        "source_text": "أمر سيدنا رسول الله صلى الله عليه وسلم خمسين من الرماة بقيادة عبد الله بن جبير بالوقوف على جبل الرماة لحماية ظهر المسلمين، وطلب منهم ألا يتركوا مواقعهم بصرف النظر عن نتيجة المعركة."
      },
      {
        "number": 7,
        "question": "ماذا فعل كثير من الرماة بعد أن كانت الغلبة للمسلمين وانهزم جيش المشركين في أول الأمر؟",
        "choices": [
          "ثبتوا في مواقعهم",
          "نزلوا من الجبل ظنًا بانتهاء المعركة",
          "لاحقوا المشركين المنهزمين",
          "عادوا إلى المدينة المنورة"
        ],
        "correct_symbol": "ب",
        "correct_answer": "نزلوا من الجبل ظنًا بانتهاء المعركة",
        "page": "81",
        "source_text": "ولما كانت الغلبة للمسلمين، وانهزم جيش المشركين أول الأمر، ظن كثير منهم أن المعركة قد انتهت، فنزلوا عن الجبل."
      },
      {
        "number": 8,
        "question": "ما النتيجة المباشرة لنزول الرماة عن جبل الرماة يوم أُحُد؟",
        "choices": [
          "انتصار المسلمين انتصارًا ساحقًا",
          "التفاف المشركين على المسلمين وإصابة الرسول صلى الله عليه وسلم",
          "انسحاب المشركين بشكل كامل",
          "تأمين ظهر المسلمين بشكل أكبر"
        ],
        "correct_symbol": "ب",
        "correct_answer": "التفاف المشركين على المسلمين وإصابة الرسول صلى الله عليه وسلم",
        "page": "81",
        "source_text": "ولما كانت الغلبة للمسلمين، وانهزم جيش المشركين أول الأمر، ظن كثير منهم أن المعركة قد انتهت، فنزلوا عن الجبل. وتنبّه المشركون لذلك، والتفوا على المسلمين، وأصابوا رسول الله صلى الله عليه وسلم، وقتلوا سبعين من الصحابة الكرام."
      },
      {
        "number": 9,
        "question": "كم عدد الصحابة الكرام الذين استشهدوا يوم أُحُد نتيجة التفاف المشركين؟",
        "choices": [
          "خمسين",
          "ستين",
          "سبعين",
          "ثمانين"
        ],
        "correct_symbol": "ج",
        "correct_answer": "سبعين",
        "page": "81",
        "source_text": "وتنبّه المشركون لذلك، والتفوا على المسلمين، وأصابوا رسول الله صلى الله عليه وسلم، وقتلوا سبعين من الصحابة الكرام."
      },
      {
        "number": 10,
        "question": "ما هو الجبل الذي يقع قرب المدينة المنورة ويُسمى جزء منه جبل الرماة؟",
        "choices": [
          "جبل ثور",
          "جبل حراء",
          "جبل أُحُد",
          "جبل النور"
        ],
        "correct_symbol": "ج",
        "correct_answer": "جبل أُحُد",
        "page": "81",
        "source_text": "جبل أُحُد: سلسلة جبال تقع قرب المدينة المنورة، ويُسمى جزء منها جبل الرماة. وقد قال عنه صلى الله عليه وسلم: «وَهذا أُحُدٌ، وَهُو َ جَبَل ٌ يُحِبُّنا وَنُحِبُّهُ»."
      },
      {
        "number": 11,
        "question": "ماذا قال النبي صلى الله عليه وسلم عن جبل أُحُد كما ورد في الحديث الشريف؟",
        "choices": [
          "«أُحُدٌ جبل من جبال الجنة»",
          "«وَهذا أُحُدٌ، وَهُو َ جَبَل ٌ يُحِبُّنا وَنُحِبُّهُ»",
          "«أُحُدٌ حصن للمسلمين»",
          "«أُحُدٌ شاهد على النصر»"
        ],
        "correct_symbol": "ب",
        "correct_answer": "«وَهذا أُحُدٌ، وَهُو َ جَبَل ٌ يُحِبُّنا وَنُحِبُّهُ»",
        "page": "81",
        "source_text": "جبل أُحُد: سلسلة جبال تقع قرب المدينة المنورة، ويُسمى جزء منها جبل الرماة. وقد قال عنه صلى الله عليه وسلم: «وَهذا أُحُدٌ، وَهُو َ جَبَل ٌ يُحِبُّنا وَنُحِبُّهُ» [رواه البخاري ومسلم]."
      },
      {
        "number": 12,
        "question": "ما هي الموضوعات الرئيسية التي تناولتها الآيات الكريمة (169-171) من سورة آل عمران؟",
        "choices": [
          "فضل طاعة الله ورسوله",
          "فضائل الشهداء",
          "الثقة بنصر الله تعالى",
          "أحكام الجهاد"
        ],
        "correct_symbol": "ب",
        "correct_answer": "فضائل الشهداء",
        "page": "82",
        "source_text": "تناولت الآيات الكريمة جانبًا مما حصل يوم أُحُد، والدروس والعبر المستفادة منه. موضوعات الآيات الكريمة: الآيات الكريمة (169-171) فضائل الشهداء."
      },
      {
        "number": 13,
        "question": "ما هي الموضوعات الرئيسية التي تناولتها الآيات الكريمة (172-174) من سورة آل عمران؟",
        "choices": [
          "فضائل الشهداء",
          "فضل طاعة الله ورسوله، والثقة بنصر الله تعالى",
          "أحكام الميراث",
          "قصص الأنبياء"
        ],
        "correct_symbol": "ب",
        "correct_answer": "فضل طاعة الله ورسوله، والثقة بنصر الله تعالى",
        "page": "82",
        "source_text": "تناولت الآيات الكريمة جانبًا مما حصل يوم أُحُد، والدروس والعبر المستفادة منه. موضوعات الآيات الكريمة: الآيات الكريمة (172-174) فضل طاعة الله ورسوله، والثقة بنصر الله تعالى."
      },
      {
        "number": 14,
        "question": "ما معنى كلمة \"القَرْح\" كما ورد في الآيات الكريمة؟",
        "choices": [
          "النصر",
          "الهزيمة",
          "الجراح",
          "الخوف"
        ],
        "correct_symbol": "ج",
        "correct_answer": "الجراح",
        "page": "82",
        "source_text": "المفردات والتراكيب: القَرْح: الجراح. تناولت الآيات الكريمة جانبًا مما حصل يوم أُحُد، والدروس والعبر المستفادة منه."
      },
      {
        "number": 15,
        "question": "ما معنى عبارة \"حَسْبُنَا اللَّهُ وَنِعْمَ الْوَكِيلُ\"؟",
        "choices": [
          "الله هو الشافي",
          "الله يكفينا وهو ناصر ومعين",
          "الله هو الرزاق",
          "الله هو الغفور الرحيم"
        ],
        "correct_symbol": "ب",
        "correct_answer": "الله يكفينا وهو ناصر ومعين",
        "page": "82",
        "source_text": "المفردات والتراكيب: حَسْبُنَا اللَّهُ وَنِعْمَ الْوَكِيلُ: الله يكفينا، وهو ناصر ومعين."
      },
      {
        "number": 16,
        "question": "ما سبب نزول الآيات الكريمة من سورة آل عمران (169-174) بعد معركة أُحُد؟",
        "choices": [
          "للوم المسلمين على هزيمتهم",
          "لبيان أخطاء القادة",
          "بشرى للمسلمين وتثبيتًا لقلوبهم بعد استشهاد عدد كبير من الصحابة",
          "لبيان أحكام جديدة للقتال"
        ],
        "correct_symbol": "ج",
        "correct_answer": "بشرى للمسلمين وتثبيتًا لقلوبهم بعد استشهاد عدد كبير من الصحابة",
        "page": "83",
        "source_text": "أصاب المسلمين همٌّ شديد بعد استشهاد عدد كبير من الصحابة الكرام في معركة أُحُد، فأنزل الله هذه الآيات الكريمة؛ بشرى لهم، وتثبيتًا لقلوبهم."
      },
      {
        "number": 17,
        "question": "ما هو الجزاء الذي أعده الله تعالى للشهداء كما بينت الآيات الكريمة من سورة آل عمران؟",
        "choices": [
          "الخلود في الدنيا",
          "أنهم أحياء عند الله تعالى ويرزقون",
          "الشفاعة لجميع الأقارب",
          "النجاة من عذاب القبر فقط"
        ],
        "correct_symbol": "ب",
        "correct_answer": "أنهم أحياء عند الله تعالى ويرزقون",
        "page": "83",
        "source_text": "وقد بينت الآيات الكريمة من سورة آل عمران بعض ما أعد الله تعالى للشهداء من جزاء، قال تعالى: ﴿ وَلَا تَحْسَبَنَّ الَّذِينَ قُتِلُوا فِي سَبِيلِ اللَّهِ أَمْوَاتًا بَلْ أَحْيَاءٌ عِنْدَ رَبِّهِمْ يُرْزَقُونَ ﴾، فذكرت أنهم أحياء عند الله تعالى، وأن الله تعالى أعد لهم في الآخرة نعمًا كثيرة تزيدهم فرحًا وسعادةً."
      },
      {
        "number": 18,
        "question": "ما دلالة قوله تعالى: ﴿ عِنْدَ رَبِّهِمْ ﴾ في وصف الشهداء؟",
        "choices": [
          "زيادة تكريم للشهداء وقربهم من الله تعالى",
          "بيان مكان رزقهم",
          "الإشارة إلى أنهم في الجنة",
          "تأكيد على موتهم"
        ],
        "correct_symbol": "أ",
        "correct_answer": "زيادة تكريم للشهداء وقربهم من الله تعالى",
        "page": "83",
        "source_text": "والتعبير بقوله تعالى: ﴿ عِنْدَ رَبِّهِمْ ﴾ فيه زيادة تكريم للشهداء؛ فهم في قرب من الله تعالى، وتقديمه على قوله تعالى: ﴿ يُرْزَقُونَ ﴾ إشارة إلى أن جوار الله تعالى أعظم رزق."
      },
      {
        "number": 19,
        "question": "ما الذي يشير إليه تقديم قوله تعالى: ﴿ عِنْدَ رَبِّهِمْ ﴾ على قوله تعالى: ﴿ يُرْزَقُونَ ﴾ في وصف الشهداء؟",
        "choices": [
          "أهمية الرزق المادي",
          "أن جوار الله تعالى أعظم رزق",
          "تأكيد على أنهم ليسوا أمواتًا",
          "بيان كثرة النعم"
        ],
        "correct_symbol": "ب",
        "correct_answer": "أن جوار الله تعالى أعظم رزق",
        "page": "83",
        "source_text": "والتعبير بقوله تعالى: ﴿ عِنْدَ رَبِّهِمْ ﴾ فيه زيادة تكريم للشهداء؛ فهم في قرب من الله تعالى، وتقديمه على قوله تعالى: ﴿ يُرْزَقُونَ ﴾ إشارة إلى أن جوار الله تعالى أعظم رزق."
      },
      {
        "number": 20,
        "question": "كيف وصف الله تعالى الشهداء في قوله: ﴿ فَرِحِينَ بِمَا آتَاهُمُ اللَّهُ مِنْ فَضْلِهِ ﴾؟",
        "choices": [
          "خائفين",
          "حزينين",
          "فرحين وراضين بفضل الله",
          "متعبين"
        ],
        "correct_symbol": "ج",
        "correct_answer": "فرحين وراضين بفضل الله",
        "page": "83",
        "source_text": "وقد وصفهم الله تعالى بالفرح والرضا بما أنعم عليهم سبحانه من فضل، قال تعالى: ﴿ فَرِحِينَ بِمَا آتَاهُمُ اللَّهُ مِنْ فَضْلِهِ ﴾."
      },
      {
        "number": 21,
        "question": "ما دلالة قوله تعالى: ﴿ وَيَسْتَبْشِرُونَ بِالَّذِينَ لَمْ يَلْحَقُوا بِهِمْ مِنْ خَلْفِهِمْ أَلَّا خَوْفٌ عَلَيْهِمْ وَلَا هُمْ يَحْزَنُونَ ﴾ بخصوص الشهداء؟",
        "choices": [
          "أنهم يخشون على من خلفهم",
          "أنهم مطمئنون لعاقبة من سيلحق بهم في درب الشهادة",
          "أنهم لا يبالون بمن خلفهم",
          "أنهم يطلبون الشفاعة لمن خلفهم"
        ],
        "correct_symbol": "ب",
        "correct_answer": "أنهم مطمئنون لعاقبة من سيلحق بهم في درب الشهادة",
        "page": "83",
        "source_text": "وقد وصفهم الله تعالى بالفرح والرضا بما أنعم عليهم سبحانه من فضل، وأخبر أنهم مطمئنون لعاقبة من سيلحق بهم في درب الشهادة، قال تعالى: ﴿ وَيَسْتَبْشِرُونَ بِالَّذِينَ لَمْ يَلْحَقُوا بِهِمْ مِنْ خَلْفِهِمْ أَلَّا خَوْفٌ عَلَيْهِمْ وَلَا هُمْ يَحْزَنُونَ ﴾."
      },
      {
        "number": 22,
        "question": "ما التوجيه الذي تضمنته الآيات الكريمة للمسلمين من قوله تعالى: ﴿ وَيَسْتَبْشِرُونَ بِالَّذِينَ لَمْ يَلْحَقُوا بِهِمْ مِنْ خَلْفِهِمْ أَلَّا خَوْفٌ عَلَيْهِمْ وَلَا هُمْ يَحْزَنُونَ ﴾؟",
        "choices": [
          "الابتعاد عن الجهاد",
          "سلوك طريق الشهداء دون خوف على الأبناء والأزواج أو حزن على متاع الدنيا",
          "التركيز على جمع الغنائم",
          "الخوف من الموت"
        ],
        "correct_symbol": "ب",
        "correct_answer": "سلوك طريق الشهداء دون خوف على الأبناء والأزواج أو حزن على متاع الدنيا",
        "page": "83",
        "source_text": "فكان في هذا توجيه للمسلمين لسلوك طريق الشهداء من دون خوف على ما عندهم من أبناء وأزواج، ومن دون حزن على ما تركوه من متاع الدنيا."
      },
      {
        "number": 23,
        "question": "ماذا قرر المشركون بعد رجوعهم من أُحُد وعدم تمكنهم من القضاء على المسلمين؟",
        "choices": [
          "الاستسلام للمسلمين",
          "إعادة الكرة بالرجوع إلى المدينة المنورة ومهاجمة المسلمين",
          "التحالف مع قبائل أخرى",
          "الانسحاب إلى مكة نهائيًا"
        ],
        "correct_symbol": "ب",
        "correct_answer": "إعادة الكرة بالرجوع إلى المدينة المنورة ومهاجمة المسلمين",
        "page": "83",
        "source_text": "لما رجع المشركون من أُحُد، قال بعضهم لبعض إنهم لم يتمكنوا من القضاء على المسلمين، فقرروا إعادة الكرة بالرجوع إلى المدينة المنورة، ومهاجمة المسلمين."
      },
      {
        "number": 24,
        "question": "ماذا أمر النبي صلى الله عليه وسلم المسلمين عندما وصله خبر قرار المشركين بالعودة لمهاجمة المدينة؟",
        "choices": [
          "البقاء في المدينة وتحصينها",
          "الخروج لملاقاة المشركين",
          "الاستعداد للدفاع عن المدينة فقط",
          "طلب المساعدة من القبائل المجاورة"
        ],
        "correct_symbol": "ب",
        "correct_answer": "الخروج لملاقاة المشركين",
        "page": "83",
        "source_text": "ولما وصل الخبر إلى سيدنا محمد صلى الله عليه وسلم، أمر بالخروج لملاقاة المشركين؛ لكي يعلموا بأن المسلمين ما يزالون أقوياء."
      },
      {
        "number": 25,
        "question": "ما الهدف من خروج المسلمين لملاقاة المشركين بعد معركة أُحُد مباشرة؟",
        "choices": [
          "الانتقام من المشركين",
          "جمع الغنائم",
          "إعلام المشركين بأن المسلمين ما يزالون أقوياء",
          "طلب الصلح من المشركين"
        ],
        "correct_symbol": "ج",
        "correct_answer": "إعلام المشركين بأن المسلمين ما يزالون أقوياء",
        "page": "83",
        "source_text": "ولما وصل الخبر إلى سيدنا محمد صلى الله عليه وسلم، أمر بالخروج لملاقاة المشركين؛ لكي يعلموا بأن المسلمين ما يزالون أقوياء، فاستجاب المسلمون لأمر رسول الله صلى الله عليه وسلم بالرغم مما أصابهم من جراح."
      },
      {
        "number": 26,
        "question": "ما هو الموقف الذي اتخذه المسلمون استجابة لأمر النبي صلى الله عليه وسلم بالخروج لملاقاة المشركين بعد أُحُد؟",
        "choices": [
          "رفضوا الخروج بسبب الجراح",
          "استجابوا لأمره بالرغم مما أصابهم من جراح",
          "ترددوا في الخروج",
          "طلبوا تأجيل الخروج"
        ],
        "correct_symbol": "ب",
        "correct_answer": "استجابوا لأمره بالرغم مما أصابهم من جراح",
        "page": "84",
        "source_text": "فاستجاب المسلمون لأمر رسول الله صلى الله عليه وسلم بالرغم مما أصابهم من جراح، قال تعالى: ﴿ الَّذِينَ اسْتَجَابُوا لِلَّهِ وَالرَّسُولِ مِنْ بَعْدِ مَا أَصَابَهُمُ الْقَرْحُ ﴾."
      },
      {
        "number": 27,
        "question": "أين تقع منطقة حَمْراء الأسد التي وصل إليها النبي صلى الله عليه وسلم بعد خروجه لملاقاة المشركين؟",
        "choices": [
          "شمال المسجد النبوي بـ 12 كيلومترًا",
          "جنوب المسجد النبوي بـ 12 كيلومترًا",
          "شرق المسجد النبوي بـ 12 كيلومترًا",
          "غرب المسجد النبوي بـ 12 كيلومترًا"
        ],
        "correct_symbol": "ب",
        "correct_answer": "جنوب المسجد النبوي بـ 12 كيلومترًا",
        "page": "84",
        "source_text": "ولما وصل النبي صلى الله عليه وسلم إلى حَمْراء الأسد (منطقة تقع على بُعْد اثني عشر كيلومترًا جنوب المسجد النبوي)، أقام صلى الله عليه وسلم فيها."
      },
      {
        "number": 28,
        "question": "ماذا فعل المشركون عندما تناهى إلى مسامعهم خبر خروج المسلمين إلى حَمْراء الأسد؟",
        "choices": [
          "تقدموا لملاقاتهم",
          "خافوا من لقائهم ورجعوا إلى مكة المكرمة",
          "أرسلوا وفدًا للتفاوض",
          "طلبوا المدد من قبائل أخرى"
        ],
        "correct_symbol": "ب",
        "correct_answer": "خافوا من لقائهم ورجعوا إلى مكة المكرمة",
        "page": "84",
        "source_text": "فلما تناهى إلى مسامع المشركين خبر خروج المسلمين، خافوا من لقائهم، ورجعوا إلى مكة المكرمة."
      },
      {
        "number": 29,
        "question": "بماذا أثنى الله تعالى على المسلمين بعد استجابتهم لأمر الله ورسوله في الخروج إلى حَمْراء الأسد؟",
        "choices": [
          "بشجاعتهم في القتال",
          "باستجابتهم لأمر الله ورسوله وثقتهم بنصر الله تعالى",
          "بكثرة عددهم",
          "بقدرتهم على التخطيط"
        ],
        "correct_symbol": "ب",
        "correct_answer": "باستجابتهم لأمر الله ورسوله وثقتهم بنصر الله تعالى",
        "page": "84",
        "source_text": "وقد أثنى الله تعالى على المسلمين؛ لاستجابتهم لأمر الله تعالى ورسوله صلى الله عليه وسلم، وثقتهم بنصر الله تعالى، ووعدهم بالأجر العظيم."
      },
      {
        "number": 30,
        "question": "ما الأجر الذي وعد الله تعالى به المسلمين الذين استجابوا لأمره ورسوله في الخروج إلى حَمْراء الأسد؟",
        "choices": [
          "النصر المؤكد في كل معركة",
          "أجرًا عظيمًا",
          "الخلاص من كل الأعداء",
          "الراحة من الجهاد"
        ],
        "correct_symbol": "ب",
        "correct_answer": "أجرًا عظيمًا",
        "page": "84",
        "source_text": "وقد أثنى الله تعالى على المسلمين؛ لاستجابتهم لأمر الله تعالى ورسوله صلى الله عليه وسلم، وثقتهم بنصر الله تعالى، ووعدهم بالأجر العظيم، قال تعالى: ﴿ فَأَثَابَهُمُ اللَّهُ أَجْرًا عَظِيمًا ﴾."
      },
      {
        "number": 31,
        "question": "بماذا مدح الله تعالى المسلمين في قوله: ﴿ الَّذِينَ قَالَ لَهُمُ النَّاسُ إِنَّ النَّاسَ قَدْ جَمَعُوا لَكُمْ فَاخْشَوْهُمْ فَزَادَهُمْ إِيمَانًا وَقَالُوا حَسْبُنَا اللَّهُ وَنِعْمَ الْوَكِيلُ ﴾؟",
        "choices": [
          "لخوفهم من المشركين",
          "لعدم خوفهم من اجتراء المشركين على حربهم",
          "لقوتهم البدنية",
          "لعدم استجابتهم لتهديدات المشركين"
        ],
        "correct_symbol": "ب",
        "correct_answer": "لعدم خوفهم من اجتراء المشركين على حربهم",
        "page": "84",
        "source_text": "كذلك مدحهم الله تعالى؛ لأنهم لم يخافوا من اجتراء المشركين على حربهم، قال تعالى: ﴿ الَّذِينَ قَالَ لَهُمُ النَّاسُ إِنَّ النَّاسَ قَدْ جَمَعُوا لَكُمْ فَاخْشَوْهُمْ فَزَادَهُمْ إِيمَانًا وَقَالُوا حَسْبُنَا اللَّهُ وَنِعْمَ الْوَكِيلُ ﴾."
      },
      {
        "number": 32,
        "question": "ماذا تعني عبارة \"حَسْبُنَا اللَّهُ وَنِعْمَ الْوَكِيلُ\" التي قالها المسلمون في موقف الشدة؟",
        "choices": [
          "نحن نعتمد على قوتنا",
          "الله سبحانه قادر على أن يكفيهم شر المشركين وإليه يلجأون وعليه يعتمدون",
          "نحن نطلب المساعدة من الحلفاء",
          "نحن نرضى بالهزيمة"
        ],
        "correct_symbol": "ب",
        "correct_answer": "الله سبحانه قادر على أن يكفيهم شر المشركين وإليه يلجأون وعليه يعتمدون",
        "page": "84",
        "source_text": "وقولهم: «حسبنا الله ونعم الوكيل» يعني أن الله سبحانه قادر على أن يكفيهم شر المشركين؛ فنحن إليه نلجأ، وعليه نعتمد، وإليه نفوض أمرنا."
      },
      {
        "number": 33,
        "question": "ما الأثر الذي ترتكز عليه الثقة بالله تعالى والرضا بقضائه في قلوب المؤمنين؟",
        "choices": [
          "الخوف من المستقبل",
          "التردد في اتخاذ القرارات",
          "ترسخ الثقة بالله تعالى والرضا بما قدره سبحانه",
          "الاعتماد على الذات فقط"
        ],
        "correct_symbol": "ج",
        "correct_answer": "ترسخ الثقة بالله تعالى والرضا بما قدره سبحانه",
        "page": "84",
        "source_text": "وبذلك تترسخ في قلوب المؤمنين الثقة بالله تعالى، والرضا بما قدره سبحانه."
      },
      {
        "number": 34,
        "question": "كيف عاد المسلمون من حَمْراء الأسد إلى المدينة المنورة؟",
        "choices": [
          "بعد قتال عنيف",
          "بعد هزيمة كبيرة",
          "من دون قتال ولم يصبهم أي أذى",
          "بعد توقيع هدنة مع المشركين"
        ],
        "correct_symbol": "ج",
        "correct_answer": "من دون قتال ولم يصبهم أي أذى",
        "page": "84",
        "source_text": "وقد رجع المسلمون من حَمْراء الأسد إلى المدينة المنورة من دون قتال، ولم يصبهم أي أذى، بسبب قيامهم بما يرضيه سبحانه، قال تعالى: ﴿ فَانْقَلَبُوا بِنِعْمَةٍ مِنَ اللَّهِ وَفَضْلٍ لَمْ يَمْسَسْهُمْ سُوءٌ وَاتَّبَعُوا رِضْوَانَ اللَّهِ ﴾."
      },
      {
        "number": 35,
        "question": "ما سبب عودة المسلمين من حَمْراء الأسد سالمين غانمين دون أن يمسهم سوء؟",
        "choices": [
          "قوتهم العسكرية",
          "ضعف المشركين",
          "قيامهم بما يرضي الله سبحانه",
          "الخطة العسكرية المحكمة"
        ],
        "correct_symbol": "ج",
        "correct_answer": "قيامهم بما يرضي الله سبحانه",
        "page": "84",
        "source_text": "وقد رجع المسلمون من حَمْراء الأسد إلى المدينة المنورة من دون قتال، ولم يصبهم أي أذى، بسبب قيامهم بما يرضيه سبحانه، قال تعالى: ﴿ فَانْقَلَبُوا بِنِعْمَةٍ مِنَ اللَّهِ وَفَضْلٍ لَمْ يَمْسَسْهُمْ سُوءٌ وَاتَّبَعُوا رِضْوَانَ اللَّهِ ﴾."
      },
      {
        "number": 36,
        "question": "ماذا قال أنس بن النضر رضي الله عنه عندما نزل أكثر الرماة عن الجبل وانهزم المسلمون يوم أُحُد؟",
        "choices": [
          "«النصر قادم لا محالة»",
          "«اللهم إني أعتذر إليك مما صنع هؤلاء (يعني المسلمين) الذين انهزموا، وأبرأ إليك مما صنع هؤلاء (يعني المشركين)»",
          "«لن نترك الجهاد أبدًا»",
          "«علينا بالصبر والثبات»"
        ],
        "correct_symbol": "ب",
        "correct_answer": "«اللهم إني أعتذر إليك مما صنع هؤلاء (يعني المسلمين) الذين انهزموا، وأبرأ إليك مما صنع هؤلاء (يعني المشركين)»",
        "page": "84",
        "source_text": "روى البخاري أنه لما نزل أكثر الرماة عن الجبل، وانهزم المسلمون، قال أنس بن النضر: «اللهم إني أعتذر إليك مما صنع هؤلاء (يعني المسلمين) الذين انهزموا، وأبرأ إليك مما صنع هؤلاء (يعني المشركين)»."
      },
      {
        "number": 37,
        "question": "ماذا قال أنس بن النضر لسعد بن معاذ عندما لقيه في المعركة؟",
        "choices": [
          "«النصر قريب»",
          "«واهًا لريح الجنة يا سعد؛ إني أجده دون أُحُد»",
          "«علينا بالثبات»",
          "«لا تيأس من رحمة الله»"
        ],
        "correct_symbol": "ب",
        "correct_answer": "«واهًا لريح الجنة يا سعد؛ إني أجده دون أُحُد»",
        "page": "84",
        "source_text": "ثم تقدم، فلقيه سعد بن معاذ، فقال: أين يا أبا عمر؟ فقال أنس: «واهًا لريح الجنة يا سعد؛ إني أجده دون أُحُد»."
      },
      {
        "number": 38,
        "question": "كيف عرفت أخت أنس بن النضر جثته بعد استشهاده في أُحُد؟",
        "choices": [
          "من وجهه",
          "من ملابسه",
          "من كثرة ما به من جراح حتى عرفته ببنانه",
          "من سيفه"
        ],
        "correct_symbol": "ج",
        "correct_answer": "من كثرة ما به من جراح حتى عرفته ببنانه",
        "page": "84",
        "source_text": "ثم مضى، فقاتل القوم حتى قُتِل، فعُرِف من كثرة ما به من جراح حتى عرفته أخته ببنانه."
      },
      {
        "number": 39,
        "question": "ما هي أول خصلة يغفرها الله للشهيد في أول دفعة من دمه كما ورد في الحديث النبوي الشريف؟",
        "choices": [
          "يرى مقعده من الجنة",
          "يغفر له في أول دفعة من دمه",
          "يُجار من عذاب القبر",
          "يأمن من الفزع الأكبر"
        ],
        "correct_symbol": "ب",
        "correct_answer": "يغفر له في أول دفعة من دمه",
        "page": "85",
        "source_text": "ذكرت السنة النبوية الشريفة عددًا من فضائل الشهداء، وذكر منها رسول الله صلى الله عليه وسلم: «يُغْفَر ُ لَه ُ في أَوَّل ِ دَفْعَة ٍ مِن ْ دَمِهِ، وَيَرى مَقْعَدَه ُ مِن َ الْجَنَّةِ، وَيُجار ُ مِن ْ عَذاب ِ الْقَبْرِ، وَيَأْمَن ُ مِن َ الْفَزَع ِ ا أل َْكْبَرِ، وَيُحَلّى حُلَّة َ ا أل ِْيمانِ، وَيُزَوَّج ُ مِن َ الْحور ِ الْعينِ، وَيُشَفَّع ُ في سَبْعين َ إِنْسانًا مِن ْ أَقارِبِهِ»."
      },
      {
        "number": 40,
        "question": "ماذا يرى الشهيد بعد أن يغفر له في أول دفعة من دمه كما ورد في الحديث النبوي الشريف؟",
        "choices": [
          "أهوال القيامة",
          "مقعده من الجنة",
          "أهله في الدنيا",
          "الملائكة"
        ],
        "correct_symbol": "ب",
        "correct_answer": "مقعده من الجنة",
        "page": "85",
        "source_text": "ذكرت السنة النبوية الشريفة عددًا من فضائل الشهداء، وذكر منها رسول الله صلى الله عليه وسلم: «يُغْفَر ُ لَه ُ في أَوَّل ِ دَفْعَة ٍ مِن ْ دَمِهِ، وَيَرى مَقْعَدَه ُ مِن َ الْجَنَّةِ، وَيُجار ُ مِن ْ عَذاب ِ الْقَبْرِ، وَيَأْمَن ُ مِن َ الْفَزَع ِ ا أل َْكْبَرِ، وَيُحَلّى حُلَّة َ ا أل ِْيمانِ، وَيُزَوَّج ُ مِن َ الْحور ِ الْعينِ، وَيُشَفَّع ُ في سَبْعين َ إِنْسانًا مِن ْ أَقارِبِهِ»."
      },
      {
        "number": 41,
        "question": "من أي عذاب يُجار الشهيد كما ورد في الحديث النبوي الشريف؟",
        "choices": [
          "عذاب النار",
          "عذاب القبر",
          "عذاب الدنيا",
          "عذاب الآخرة"
        ],
        "correct_symbol": "ب",
        "correct_answer": "عذاب القبر",
        "page": "85",
        "source_text": "ذكرت السنة النبوية الشريفة عددًا من فضائل الشهداء، وذكر منها رسول الله صلى الله عليه وسلم: «يُغْفَر ُ لَه ُ في أَوَّل ِ دَفْعَة ٍ مِن ْ دَمِهِ، وَيَرى مَقْعَدَه ُ مِن َ الْجَنَّةِ، وَيُجار ُ مِن ْ عَذاب ِ الْقَبْرِ، وَيَأْمَن ُ مِن َ الْفَزَع ِ ا أل َْكْبَرِ، وَيُحَلّى حُلَّة َ ا أل ِْيمانِ، وَيُزَوَّج ُ مِن َ الْحور ِ الْعينِ، وَيُشَفَّع ُ في سَبْعين َ إِنْسانًا مِن ْ أَقارِبِهِ»."
      },
      {
        "number": 42,
        "question": "مما يأمن الشهيد كما ورد في الحديث النبوي الشريف؟",
        "choices": [
          "من الفقر",
          "من المرض",
          "من الفزع الأكبر",
          "من الوحدة"
        ],
        "correct_symbol": "ج",
        "correct_answer": "من الفزع الأكبر",
        "page": "85",
        "source_text": "ذكرت السنة النبوية الشريفة عددًا من فضائل الشهداء، وذكر منها رسول الله صلى الله عليه وسلم: «يُغْفَر ُ لَه ُ في أَوَّل ِ دَفْعَة ٍ مِن ْ دَمِهِ، وَيَرى مَقْعَدَه ُ مِن َ الْجَنَّةِ، وَيُجار ُ مِن ْ عَذاب ِ الْقَبْرِ، وَيَأْمَن ُ مِن َ الْفَزَع ِ ا أل َْكْبَرِ، وَيُحَلّى حُلَّة َ ا أل ِْيمانِ، وَيُزَوَّج ُ مِن َ الْحور ِ الْعينِ، وَيُشَفَّع ُ في سَبْعين َ إِنْسانًا مِن ْ أَقارِبِهِ»."
      },
      {
        "number": 43,
        "question": "ما المقصود بـ \"الفزع الأكبر\" كما ورد في الحديث النبوي الشريف؟",
        "choices": [
          "أهوال الدنيا",
          "أهوال الحساب يوم القيامة",
          "أهوال القبر",
          "أهوال الموت"
        ],
        "correct_symbol": "ب",
        "correct_answer": "أهوال الحساب يوم القيامة",
        "page": "85",
        "source_text": "ذكرت السنة النبوية الشريفة عددًا من فضائل الشهداء، وذكر منها رسول الله صلى الله عليه وسلم: «يُغْفَر ُ لَه ُ في أَوَّل ِ دَفْعَة ٍ مِن ْ دَمِهِ، وَيَرى مَقْعَدَه ُ مِن َ الْجَنَّةِ، وَيُجار ُ مِن ْ عَذاب ِ الْقَبْرِ، وَيَأْمَن ُ مِن َ الْفَزَع ِ ا أل َْكْبَرِ، وَيُحَلّى حُلَّة َ ا أل ِْيمانِ، وَيُزَوَّج ُ مِن َ الْحور ِ الْعينِ، وَيُشَفَّع ُ في سَبْعين َ إِنْسانًا مِن ْ أَقارِبِهِ». (الْفَزَع ِ ا أل َْكْبَرِ: أهوال الحساب يوم القيامة)."
      },
      {
        "number": 44,
        "question": "بماذا يُحلّى الشهيد كما ورد في الحديث النبوي الشريف؟",
        "choices": [
          "حلة الإمارة",
          "حلة الإيمان",
          "حلة الشجاعة",
          "حلة النصر"
        ],
        "correct_symbol": "ب",
        "correct_answer": "حلة الإيمان",
        "page": "85",
        "source_text": "ذكرت السنة النبوية الشريفة عددًا من فضائل الشهداء، وذكر منها رسول الله صلى الله عليه وسلم: «يُغْفَر ُ لَه ُ في أَوَّل ِ دَفْعَة ٍ مِن ْ دَمِهِ، وَيَرى مَقْعَدَه ُ مِن َ الْجَنَّةِ، وَيُجار ُ مِن ْ عَذاب ِ الْقَبْرِ، وَيَأْمَن ُ مِن َ الْفَزَع ِ ا أل َْكْبَرِ، وَيُحَلّى حُلَّة َ ا أل ِْيمانِ، وَيُزَوَّج ُ مِن َ الْحور ِ الْعينِ، وَيُشَفَّع ُ في سَبْعين َ إِنْسانًا مِن ْ أَقارِبِهِ»."
      },
      {
        "number": 45,
        "question": "بمن يُزوج الشهيد كما ورد في الحديث النبوي الشريف؟",
        "choices": [
          "من نساء الدنيا",
          "من الحور العين",
          "من الملائكة",
          "من أقاربه"
        ],
        "correct_symbol": "ب",
        "correct_answer": "من الحور العين",
        "page": "85",
        "source_text": "ذكرت السنة النبوية الشريفة عددًا من فضائل الشهداء، وذكر منها رسول الله صلى الله عليه وسلم: «يُغْفَر ُ لَه ُ في أَوَّل ِ دَفْعَة ٍ مِن ْ دَمِهِ، وَيَرى مَقْعَدَه ُ مِن َ الْجَنَّةِ، وَيُجار ُ مِن ْ عَذاب ِ الْقَبْرِ، وَيَأْمَن ُ مِن َ الْفَزَع ِ ا أل َْكْبَرِ، وَيُحَلّى حُلَّة َ ا أل ِْيمانِ، وَيُزَوَّج ُ مِن َ الْحور ِ الْعينِ، وَيُشَفَّع ُ في سَبْعين َ إِنْسانًا مِن ْ أَقارِبِهِ»."
      },
      {
        "number": 46,
        "question": "كم عدد الأقارب الذين يُشفع فيهم الشهيد كما ورد في الحديث النبوي الشريف؟",
        "choices": [
          "عشرة",
          "عشرين",
          "خمسين",
          "سبعين"
        ],
        "correct_symbol": "د",
        "correct_answer": "سبعين",
        "page": "85",
        "source_text": "ذكرت السنة النبوية الشريفة عددًا من فضائل الشهداء، وذكر منها رسول الله صلى الله عليه وسلم: «يُغْفَر ُ لَه ُ في أَوَّل ِ دَفْعَة ٍ مِن ْ دَمِهِ، وَيَرى مَقْعَدَه ُ مِن َ الْجَنَّةِ، وَيُجار ُ مِن ْ عَذاب ِ الْقَبْرِ، وَيَأْمَن ُ مِن َ الْفَزَع ِ ا أل َْكْبَرِ، وَيُحَلّى حُلَّة َ ا أل ِْيمانِ، وَيُزَوَّج ُ مِن َ الْحور ِ الْعينِ، وَيُشَفَّع ُ في سَبْعين َ إِنْسانًا مِن ْ أَقارِبِهِ»."
      },
      {
        "number": 47,
        "question": "في أي عام استشهد العديد من شهداء الأردن في معركة باب الواد دفاعًا عن المقدسات؟",
        "choices": [
          "1948 م",
          "1967 م",
          "1968 م",
          "1973 م"
        ],
        "correct_symbol": "أ",
        "correct_answer": "1948 م",
        "page": "85",
        "source_text": "وقد قدم الأردن كثيرًا من الشهداء الذين دافعوا عن المقدسات بكل شجاعة، واستشهد العديد منهم في معركة باب الواد عام 1948 م، ومعارك القدس عام 1967 م، ومعركة الكرامة عام 1968 م دفاعًا عن المسجد الأقصى المبارك."
      },
      {
        "number": 48,
        "question": "في أي عام استشهد العديد من شهداء الأردن في معارك القدس دفاعًا عن المسجد الأقصى المبارك؟",
        "choices": [
          "1948 م",
          "1967 م",
          "1968 م",
          "1973 م"
        ],
        "correct_symbol": "ب",
        "correct_answer": "1967 م",
        "page": "85",
        "source_text": "وقد قدم الأردن كثيرًا من الشهداء الذين دافعوا عن المقدسات بكل شجاعة، واستشهد العديد منهم في معركة باب الواد عام 1948 م، ومعارك القدس عام 1967 م، ومعركة الكرامة عام 1968 م دفاعًا عن المسجد الأقصى المبارك."
      },
      {
        "number": 49,
        "question": "في أي عام استشهد العديد من شهداء الأردن في معركة الكرامة دفاعًا عن المسجد الأقصى المبارك؟",
        "choices": [
          "1948 م",
          "1967 م",
          "1968 م",
          "1973 م"
        ],
        "correct_symbol": "ج",
        "correct_answer": "1968 م",
        "page": "85",
        "source_text": "وقد قدم الأردن كثيرًا من الشهداء الذين دافعوا عن المقدسات بكل شجاعة، واستشهد العديد منهم في معركة باب الواد عام 1948 م، ومعارك القدس عام 1967 م، ومعركة الكرامة عام 1968 م دفاعًا عن المسجد الأقصى المبارك."
      },
      {
        "number": 50,
        "question": "ما هو المكان المقدس الذي دافع عنه شهداء الأردن في معارك باب الواد والقدس والكرامة؟",
        "choices": [
          "المسجد الحرام",
          "المسجد النبوي",
          "المسجد الأقصى المبارك",
          "المسجد الأموي"
        ],
        "correct_symbol": "ج",
        "correct_answer": "المسجد الأقصى المبارك",
        "page": "85",
        "source_text": "وقد قدم الأردن كثيرًا من الشهداء الذين دافعوا عن المقدسات بكل شجاعة، واستشهد العديد منهم في معركة باب الواد عام 1948 م، ومعارك القدس عام 1967 م، ومعركة الكرامة عام 1968 م دفاعًا عن المسجد الأقصى المبارك."
      }
    ]