[
      {
        "number": 1,
        "question": "ما الذي يُعد مقصدًا من المقاصد الكبرى للشريعة الإسلامية لما يمثله من استمرار للنوع الإنساني؟",
        "choices": [
          "حفظ النفس",
          "حفظ العقل",
          "حفظ النسل",
          "حفظ المال"
        ],
        "correct_symbol": "ج",
        "correct_answer": "حفظ النسل",
        "page": "141",
        "source_text": "يُعد حفظ النسل مقصدًا من المقاصد الكبرى للشريعة الإسلامية؛ لما يمثله من استمرار للنوع الإنساني. وقد جعل الإسلام الزواج وسيلة لذلك."
      },
      {
        "number": 2,
        "question": "ما الوسيلة التي جعلها الإسلام لاستمرار النوع الإنساني وحفظ النسل؟",
        "choices": [
          "الجهاد",
          "الزواج",
          "العمل",
          "العلم"
        ],
        "correct_symbol": "ب",
        "correct_answer": "الزواج",
        "page": "141",
        "source_text": "يُعد حفظ النسل مقصدًا من المقاصد الكبرى للشريعة الإسلامية؛ لما يمثله من استمرار للنوع الإنساني. وقد جعل الإسلام الزواج وسيلة لذلك."
      },
      {
        "number": 3,
        "question": "ما الذي حرمه الإسلام ورتب عليه العقاب في الدنيا والوعيد في الآخرة؟",
        "choices": [
          "قتل النفس أو الإضرار بها",
          "عدم الزواج",
          "عدم الإنجاب",
          "عدم العمل"
        ],
        "correct_symbol": "أ",
        "correct_answer": "قتل النفس أو الإضرار بها",
        "page": "141",
        "source_text": "حرم الإسلام قتل النفس، أو الإضرار بها بأي صورة من الصور، ورتب على ذلك العقاب في الدنيا، والوعيد في الآخرة."
      },
      {
        "number": 4,
        "question": "ما العقوبة المترتبة على قتل النفس أو الإضرار بها في الدنيا والآخرة؟",
        "choices": [
          "الوعيد في الدنيا والعقاب في الآخرة",
          "العقاب في الدنيا والوعيد في الآخرة",
          "المغفرة في الدنيا والجنة في الآخرة",
          "التوبة في الدنيا والرحمة في الآخرة"
        ],
        "correct_symbol": "ب",
        "correct_answer": "العقاب في الدنيا والوعيد في الآخرة",
        "page": "141",
        "source_text": "حرم الإسلام قتل النفس، أو الإضرار بها بأي صورة من الصور، ورتب على ذلك العقاب في الدنيا، والوعيد في الآخرة."
      },
      {
        "number": 5,
        "question": "في قوله تعالى: ﴿مِنْ أَجْلِ ذَٰلِكَ كَتَبْنَا عَلَىٰ بَنِي إِسْرَائِيلَ أَنَّهُ مَن قَتَلَ نَفْسًا بِغَيْرِ نَفْسٍ أَوْ فَسَادٍ فِي الْأَرْضِ فَكَأَنَّمَا قَتَلَ النَّاسَ جَمِيعًا﴾ [المائدة: ٣٢]، ما الحكمة من اعتبار قتل نفس واحدة ظلماً بمنزلة قتل الناس جميعًا؟",
        "choices": [
          "لأن النفس البشرية لا تقدر بثمن",
          "لأنها تخل بالأمن المجتمعي",
          "لأنها اعتداء على حق الله",
          "لأنها تسبب الفوضى"
        ],
        "correct_symbol": "أ",
        "correct_answer": "لأن النفس البشرية لا تقدر بثمن",
        "page": "141",
        "source_text": "أتدبر مع أفراد مجموعتي قوله تعالى: ﴿مِنْ أَجْلِ ذَٰلِكَ كَتَبْنَا عَلَىٰ بَنِي إِسْرَائِيلَ أَنَّهُ مَن قَتَلَ نَفْسًا بِغَيْرِ نَفْسٍ أَوْ فَسَادٍ فِي الْأَرْضِ فَكَأَنَّمَا قَتَلَ النَّاسَ جَمِيعًا﴾، ثم أبين الحكمة من اعتبار قتل نفس واحدة ظلماً بمنزلة قتل الناس جميعًا."
      },
      {
        "number": 6,
        "question": "ما الذي اعتنى به الإسلام واعتبره من أهم مقاصد الزواج؟",
        "choices": [
          "المال",
          "النسل",
          "العمل",
          "العلم"
        ],
        "correct_symbol": "ب",
        "correct_answer": "النسل",
        "page": "141",
        "source_text": "اعتنى الإسلام بالنسل الذي هو من أهم مقاصد الزواج."
      },
      {
        "number": 7,
        "question": "ما مفهوم تنظيم النسل؟",
        "choices": [
          "اتخاذ إجراءات تمنع الحمل بصفة دائمة",
          "تعمد إسقاط الحمل في غير موعده الطبيعي",
          "اتخاذ وسيلة مشروعة لإيجاد مدد زمنية متباعدة بين مرات الحمل",
          "منع الحمل بأي وسيلة ممكنة"
        ],
        "correct_symbol": "ج",
        "correct_answer": "اتخاذ وسيلة مشروعة لإيجاد مدد زمنية متباعدة بين مرات الحمل",
        "page": "142",
        "source_text": "تنظيم النسل: هو اتخاذ وسيلة مشروعة لإيجاد مدد زمنية متباعدة بين مرات الحمل."
      },
      {
        "number": 8,
        "question": "ما حكم تنظيم النسل عند توافر أسبابه؟",
        "choices": [
          "محرم",
          "مكروه",
          "مباح",
          "واجب"
        ],
        "correct_symbol": "ج",
        "correct_answer": "مباح",
        "page": "142",
        "source_text": "أباح الإسلام تنظيم النسل عند توافر أسبابه، وجعله قرارًا يتم بموافقة الزوجين."
      },
      {
        "number": 9,
        "question": "ما الشرط الأساسي لإباحة تنظيم النسل؟",
        "choices": [
          "موافقة الزوجين",
          "موافقة الطبيب",
          "موافقة الأهل",
          "موافقة الدولة"
        ],
        "correct_symbol": "أ",
        "correct_answer": "موافقة الزوجين",
        "page": "142",
        "source_text": "أباح الإسلام تنظيم النسل عند توافر أسبابه، وجعله قرارًا يتم بموافقة الزوجين."
      },
      {
        "number": 10,
        "question": "ما الدليل الشرعي على إباحة تنظيم النسل من فعل الصحابة في عهد النبي صلى الله عليه وسلم؟",
        "choices": [
          "الزواج",
          "العزل",
          "الصيام",
          "الصدقة"
        ],
        "correct_symbol": "ب",
        "correct_answer": "العزل",
        "page": "142",
        "source_text": "فقد أباح النبي صلى الله عليه وسلم لأصحابه وسيلة العزل، جاء عن جابر قال: «كنا نعزل على عهد رسول الله صلى الله عليه وسلم، فبلغ ذلك نبي الله، فلم ينهنا» [رواه مسلم]."
      },
      {
        "number": 11,
        "question": "ماذا يدل قول جابر رضي الله عنه: «كنا نعزل على عهد رسول الله صلى الله عليه وسلم، فبلغ ذلك نبي الله، فلم ينهنا»؟",
        "choices": [
          "تحريم العزل",
          "وجوب العزل",
          "إباحة العزل",
          "كراهة العزل"
        ],
        "correct_symbol": "ج",
        "correct_answer": "إباحة العزل",
        "page": "142",
        "source_text": "جاء عن جابر قال: «كنا نعزل على عهد رسول الله صلى الله عليه وسلم، فبلغ ذلك نبي الله، فلم ينهنا» [رواه مسلم]. وهذا يدل على أن تنظيم النسل مباح."
      },
      {
        "number": 12,
        "question": "من أسباب إباحة تنظيم النسل الحفاظ على صحة الأم الإنجابية ودفع الضرر عنها، خاصة إذا كانت الأم:",
        "choices": [
          "تلد ولادة طبيعية",
          "لا تلد ولادة طبيعية وتحتاج لعملية كل مرة",
          "لا ترغب في الإنجاب",
          "كبيرة في السن"
        ],
        "correct_symbol": "ب",
        "correct_answer": "لا تلد ولادة طبيعية وتحتاج لعملية كل مرة",
        "page": "142",
        "source_text": "من أسباب إباحة تنظيم النسل: الحفاظ على الصحة الإنجابية للأم، ودفع الضرر عنها، وبخاصة إذا كانت لا تلد ولادة طبيعية، وتحتاج إلى إجراء عملية كل مرة، والخشية على حياة الأم بسبب تتابع الحمل."
      },
      {
        "number": 13,
        "question": "ما الخشية التي تبرر تنظيم النسل للحفاظ على صحة الأم الإنجابية؟",
        "choices": [
          "الخشية على رزق الأبناء",
          "الخشية على حياة الأم بسبب تتابع الحمل",
          "الخشية من عدم الإنجاب",
          "الخشية من كثرة الأبناء"
        ],
        "correct_symbol": "ب",
        "correct_answer": "الخشية على حياة الأم بسبب تتابع الحمل",
        "page": "142",
        "source_text": "من أسباب إباحة تنظيم النسل: الحفاظ على الصحة الإنجابية للأم، ودفع الضرر عنها، وبخاصة إذا كانت لا تلد ولادة طبيعية، وتحتاج إلى إجراء عملية كل مرة، والخشية على حياة الأم بسبب تتابع الحمل."
      },
      {
        "number": 14,
        "question": "ما الهدف من منح الزوجين الوقت اللازم للعناية بأطفالهما من خلال تنظيم النسل؟",
        "choices": [
          "لكي لا تسوء صحتهم وتختل تربيتهم",
          "للتفرغ للدراسة",
          "لتحقيق مصالح شخصية",
          "لتوفير المال"
        ],
        "correct_symbol": "أ",
        "correct_answer": "لكي لا تسوء صحتهم وتختل تربيتهم",
        "page": "142",
        "source_text": "من أسباب إباحة تنظيم النسل: منح الزوجين الوقت اللازم للعناية بأطفالهما؛ لكيلا تسوء صحتهم، وتختل تربيتهم؛ تخفيفًا عن الزوجين، وتحقيقًا لمصلحة الأولاد."
      },
      {
        "number": 15,
        "question": "ما المصلحة التي تتحقق للأولاد من خلال منح الزوجين الوقت الكافي للعناية بهم؟",
        "choices": [
          "تحقيق مصلحة الأبوين",
          "تحقيق مصلحة الأولاد",
          "تحقيق مصلحة المجتمع",
          "تحقيق مصلحة الأقارب"
        ],
        "correct_symbol": "ب",
        "correct_answer": "تحقيق مصلحة الأولاد",
        "page": "142",
        "source_text": "من أسباب إباحة تنظيم النسل: منح الزوجين الوقت اللازم للعناية بأطفالهما؛ لكيلا تسوء صحتهم، وتختل تربيتهم؛ تخفيفًا عن الزوجين، وتحقيقًا لمصلحة الأولاد."
      },
      {
        "number": 16,
        "question": "إذا وجد مرض ضار أو معدٍ في الزوجين أو أحدهما ويرجى شفاؤه، وقد ينتقل إلى أولادهما، فماذا ينصح به؟",
        "choices": [
          "تحديد النسل بشكل دائم",
          "تأخير الحمل لحين العلاج",
          "الإنجاب مع أخذ الاحتياطات",
          "عدم الإنجاب مطلقًا"
        ],
        "correct_symbol": "ب",
        "correct_answer": "تأخير الحمل لحين العلاج",
        "page": "142",
        "source_text": "من أسباب إباحة تنظيم النسل: وجود مرض ضار أو معدٍ في الزوجين أو في أحدهما، يرجى شفاؤه، وقد ينتقل إلى أولادهما، فينصح بتأخير الحمل لحين العلاج."
      },
      {
        "number": 17,
        "question": "ما القاعدة الفقهية التي يستند إليها جواز تأخير الحمل في حال وجود مرض يرجى شفاؤه، كما ورد في الحديث الشريف؟",
        "choices": [
          "الضرر يزال",
          "الضرورات تبيح المحظورات",
          "لا ضرر ولا ضرار",
          "المشقة تجلب التيسير"
        ],
        "correct_symbol": "ج",
        "correct_answer": "لا ضرر ولا ضرار",
        "page": "142",
        "source_text": "وجود مرض ضار أو معدٍ في الزوجين أو في أحدهما، يرجى شفاؤه، وقد ينتقل إلى أولادهما، فينصح بتأخير الحمل لحين العلاج. قال رسول الله صلى الله عليه وسلم: «لا ضرر ولا ضرار» [رواه مالك]."
      },
      {
        "number": 18,
        "question": "من الحاجات الاجتماعية والاقتصادية المعتبرة شرعًا التي تبيح تنظيم النسل:",
        "choices": [
          "الرغبة في الثراء",
          "التفرغ للدراسة وطبيعة العمل",
          "الخوف من الفقر",
          "عدم الرغبة في تحمل المسؤولية"
        ],
        "correct_symbol": "ب",
        "correct_answer": "التفرغ للدراسة وطبيعة العمل",
        "page": "142",
        "source_text": "من أسباب إباحة تنظيم النسل: حاجات اجتماعية واقتصادية معتبرة شرعًا، مثل: التفرغ للدراسة، وطبيعة العمل."
      },
      {
        "number": 19,
        "question": "ما مفهوم العزل؟",
        "choices": [
          "وسيلة من وسائل منع الحمل",
          "وسيلة لتحديد النسل بصفة دائمة",
          "وسيلة لإسقاط الحمل",
          "وسيلة لتأخير الزواج"
        ],
        "correct_symbol": "أ",
        "correct_answer": "وسيلة من وسائل منع الحمل",
        "page": "142",
        "source_text": "العزل: وسيلة من وسائل منع الحمل."
      },
      {
        "number": 20,
        "question": "ما الشرط الأساسي لإباحة استخدام الوسائل الحديثة المشروعة التي تمنع حدوث الحمل؟",
        "choices": [
          "أن تكون مكلفة",
          "أن تكون سهلة الاستخدام",
          "أن يؤمن ضررها",
          "أن تكون دائمة المفعول"
        ],
        "correct_symbol": "ج",
        "correct_answer": "أن يؤمن ضررها",
        "page": "142",
        "source_text": "يباح استخدام الوسائل الحديثة المشروعة التي تمنع حدوث الحمل إن أمن ضررها."
      },
      {
        "number": 21,
        "question": "ماذا تشمل الصحة الإنجابية؟",
        "choices": [
          "السلامة البدنية فقط",
          "السلامة النفسية فقط",
          "السلامة البدنية والنفسية لعيش حياة هنيئة وآمنة",
          "السلامة الاجتماعية والاقتصادية"
        ],
        "correct_symbol": "ج",
        "correct_answer": "السلامة البدنية والنفسية لعيش حياة هنيئة وآمنة",
        "page": "142",
        "source_text": "الصحة الإنجابية: السلامة البدنية والنفسية لعيش حياة هنيئة وآمنة."
      },
      {
        "number": 22,
        "question": "ما مفهوم تحديد النسل؟",
        "choices": [
          "اتخاذ وسيلة مشروعة لإيجاد مدد زمنية متباعدة بين مرات الحمل",
          "اتخاذ الإجراءات التي تمنع الحمل بصفة دائمة",
          "تعمد إسقاط الحمل في غير موعده الطبيعي",
          "تأخير الحمل لحين العلاج"
        ],
        "correct_symbol": "ب",
        "correct_answer": "اتخاذ الإجراءات التي تمنع الحمل بصفة دائمة",
        "page": "143",
        "source_text": "تحديد النسل: هو اتخاذ الإجراءات التي تمنع الحمل بصفة دائمة، مثل: استئصال رحم المرأة؛ سواء أكان ذلك بعد إنجاب عدد من الأولاد، أم ابتداء من غير ضرورة طبية."
      },
      {
        "number": 23,
        "question": "ما حكم تحديد النسل بهذا الوصف (بصفة دائمة ومن غير ضرورة طبية)؟",
        "choices": [
          "مباح",
          "مكروه",
          "محرم",
          "واجب"
        ],
        "correct_symbol": "ج",
        "correct_answer": "محرم",
        "page": "143",
        "source_text": "يعد تحديد النسل بهذا الوصف أمرًا محرمًا، استنادًا إلى الدليلين الآتيين."
      },
      {
        "number": 24,
        "question": "ما الدليل الأول على تحريم تحديد النسل؟",
        "choices": [
          "معارضته حكمة التشريع الإسلامي في الحث على الزواج والتكاثر",
          "معارضته العقيدة الإسلامية في الرزق",
          "معارضته لمصلحة الأولاد",
          "معارضته للصحة الإنجابية"
        ],
        "correct_symbol": "أ",
        "correct_answer": "معارضته حكمة التشريع الإسلامي في الحث على الزواج والتكاثر",
        "page": "143",
        "source_text": "يعد تحديد النسل بهذا الوصف أمرًا محرمًا، استنادًا إلى الدليلين الآتيين: معارضته حكمة التشريع الإسلامي في الحث على الزواج، والموالتكاثر الذي يسهم في تحقيق غاية الأرض."
      },
      {
        "number": 25,
        "question": "ما الغاية التي يسهم التكاثر في تحقيقها، والتي يعارضها تحديد النسل؟",
        "choices": [
          "غاية السماء",
          "غاية الأرض",
          "غاية الإنسان",
          "غاية العبادة"
        ],
        "correct_symbol": "ب",
        "correct_answer": "غاية الأرض",
        "page": "143",
        "source_text": "يعد تحديد النسل بهذا الوصف أمرًا محرمًا، استنادًا إلى الدليلين الآتيين: معارضته حكمة التشريع الإسلامي في الحث على الزواج، والموالتكاثر الذي يسهم في تحقيق غاية الأرض."
      },
      {
        "number": 26,
        "question": "ما الدليل الثاني على تحريم تحديد النسل إذا كان لداعي الخوف على الرزق؟",
        "choices": [
          "معارضته حكمة التشريع الإسلامي",
          "معارضته العقيدة الإسلامية",
          "معارضته لمصلحة الزوجين",
          "معارضته لمصلحة المجتمع"
        ],
        "correct_symbol": "ب",
        "correct_answer": "معارضته العقيدة الإسلامية",
        "page": "143",
        "source_text": "يعد تحديد النسل بهذا الوصف أمرًا محرمًا، استنادًا إلى الدليلين الآتيين: معارضته العقيدة الإسلامية أن الله إذا كان ذلك لداعي الخوف على الرزق؛ فقد بينت النصوص الشرعية أن الله تعالى تكفل برزق الأبناء والآباء."
      },
      {
        "number": 27,
        "question": "في قوله تعالى: ﴿وَلَا تَقْتُلُوا أَوْلَادَكُمْ خَشْيَةَ إِمْلَاقٍ ۖ نَّحْنُ نَرْزُقُهُمْ وَإِيَّاكُمْ ۚ إِنَّ قَتْلَهُمْ كَانَ خِطْئًا كَبِيرًا﴾ [الإسراء: ٣١]، ما الذي تكفل الله به؟",
        "choices": [
          "رزق الأبناء فقط",
          "رزق الآباء فقط",
          "رزق الأبناء والآباء",
          "رزق الأمهات فقط"
        ],
        "correct_symbol": "ج",
        "correct_answer": "رزق الأبناء والآباء",
        "page": "143",
        "source_text": "معارضته العقيدة الإسلامية أن الله إذا كان ذلك لداعي الخوف على الرزق؛ فقد بينت النصوص الشرعية أن الله تعالى تكفل برزق الأبناء والآباء، قال تعالى: ﴿وَلَا تَقْتُلُوا أَوْلَادَكُمْ خَشْيَةَ إِمْلَاقٍ ۖ نَّحْنُ نَرْزُقُهُمْ وَإِيَّاكُمْ ۚ إِنَّ قَتْلَهُمْ كَانَ خِطْئًا كَبِيرًا﴾."
      },
      {
        "number": 28,
        "question": "متى يجوز تحديد النسل؟",
        "choices": [
          "إذا وجدت ضرورة",
          "إذا رغب الزوجان بذلك",
          "إذا كان هناك خوف من الرزق",
          "إذا كان هناك عدد كبير من الأولاد"
        ],
        "correct_symbol": "أ",
        "correct_answer": "إذا وجدت ضرورة",
        "page": "143",
        "source_text": "أما إذا وجدت ضرورة فلا مانع من تحديد النسل ما دامت الأسباب قائمة؛ بقاعدة (الضرورات تبيح المحظورات)."
      },
      {
        "number": 29,
        "question": "ما القاعدة الفقهية التي تبيح تحديد النسل عند وجود ضرورة؟",
        "choices": [
          "المشقة تجلب التيسير",
          "الضرر يزال",
          "الضرورات تبيح المحظورات",
          "العادة محكمة"
        ],
        "correct_symbol": "ج",
        "correct_answer": "الضرورات تبيح المحظورات",
        "page": "143",
        "source_text": "أما إذا وجدت ضرورة فلا مانع من تحديد النسل ما دامت الأسباب قائمة؛ بقاعدة (الضرورات تبيح المحظورات)."
      },
      {
        "number": 30,
        "question": "من الأمثلة على الضرورة التي تبيح تحديد النسل:",
        "choices": [
          "إصابة الزوجين بمرض يرجى شفاؤه",
          "الخوف من قلة الرزق",
          "إصابة الزوجين أو أحدهما بمرض ضار ومعدٍ لا يمكن شفاؤه وينتقل إلى الأطفال",
          "التفرغ للدراسة"
        ],
        "correct_symbol": "ج",
        "correct_answer": "إصابة الزوجين أو أحدهما بمرض ضار ومعدٍ لا يمكن شفاؤه وينتقل إلى الأطفال",
        "page": "143",
        "source_text": "ومن الأمثلة على ذلك: إصابة الزوجين أو أحدهما بمرض ضار ومعدٍ لا يمكن شفاؤه، وينتقل إلى الأطفال."
      },
      {
        "number": 31,
        "question": "ما الشرط الواجب توافره عند تحديد النسل بسبب الخوف المؤكد على حياة الأم؟",
        "choices": [
          "موافقة الأهل",
          "استشارة الطبيب الثقة المؤتمن",
          "موافقة الزوجة فقط",
          "موافقة الزوج فقط"
        ],
        "correct_symbol": "ب",
        "correct_answer": "استشارة الطبيب الثقة المؤتمن",
        "page": "143",
        "source_text": "ومن الأمثلة على ذلك: الخوف المؤكد على حياة الأم بسبب الحمل؛ بشرط أن يكون ذلك بعد استشارة الطبيب الثقة المؤتمن."
      },
      {
        "number": 32,
        "question": "أي من الأمثلة الآتية يعد تنظيمًا للنسل؟",
        "choices": [
          "استئصال رحم المرأة",
          "امتناع المرأة عن الإنجاب حتى تكمل دراستها",
          "تشريع قانون ملزم للأسر بالتوقف عن الإنجاب بعد عدد معين من الأطفال",
          "عدم الإنجاب بسبب مرض لا يرجى شفاؤه"
        ],
        "correct_symbol": "ب",
        "correct_answer": "امتناع المرأة عن الإنجاب حتى تكمل دراستها",
        "page": "143",
        "source_text": "امتناع المرأة عن الإنجاب حتى تكمل دراستها يصنف تنظيمًا للنسل."
      },
      {
        "number": 33,
        "question": "أي من الأمثلة الآتية يعد تحديدًا للنسل؟",
        "choices": [
          "عدم حمل الزوجة حتى تشفى من مرضها",
          "استئصال رحم المرأة",
          "المباعدة بين مرات الحمل بوسائل مشروعة",
          "التفرغ للدراسة"
        ],
        "correct_symbol": "ب",
        "correct_answer": "استئصال رحم المرأة",
        "page": "143",
        "source_text": "استئصال رحم المرأة يصنف تحديدًا للنسل."
      },
      {
        "number": 34,
        "question": "ما معنى القاعدة الفقهية \"الضرورات تبيح المحظورات\"؟",
        "choices": [
          "أن المنهي عنه يباح فعله عند الضرورة والحاجة الشديدة",
          "أن كل محظور مباح في أي وقت",
          "أن الضرورة تلغي التحريم مطلقًا",
          "أن الحاجة تبيح كل شيء"
        ],
        "correct_symbol": "أ",
        "correct_answer": "أن المنهي عنه يباح فعله عند الضرورة والحاجة الشديدة",
        "page": "143",
        "source_text": "الضرورات تبيح المحظورات: قاعدة فقهية تعني أن المنهي عنه شرعًا يباح فعله عند الضرورة والحاجة الشديدة."
      },
      {
        "number": 35,
        "question": "ما المثال الذي يوضح تطبيق قاعدة \"الضرورات تبيح المحظورات\"؟",
        "choices": [
          "إباحة الصيد في الحرم",
          "إباحة أكل الميتة في حال الجوع الشديد",
          "إباحة الربا عند الحاجة",
          "إباحة السرقة عند الفقر"
        ],
        "correct_symbol": "ب",
        "correct_answer": "إباحة أكل الميتة في حال الجوع الشديد",
        "page": "143",
        "source_text": "من الأمثلة على ذلك: إباحة أكل الميتة في حال الجوع الشديد، كالمجاعات."
      },
      {
        "number": 36,
        "question": "ما مفهوم الإجهاض؟",
        "choices": [
          "اتخاذ إجراءات تمنع الحمل بصفة دائمة",
          "اتخاذ وسيلة مشروعة لإيجاد مدد زمنية متباعدة بين مرات الحمل",
          "تعمد إسقاط الحمل في غير موعده الطبيعي، وبلا ضرورة، وبأي وسيلة",
          "تأخير الحمل لحين العلاج"
        ],
        "correct_symbol": "ج",
        "correct_answer": "تعمد إسقاط الحمل في غير موعده الطبيعي، وبلا ضرورة، وبأي وسيلة",
        "page": "144",
        "source_text": "الإجهاض: هو تعمد إسقاط الحمل في غير موعده الطبيعي، وبلا ضرورة، وبأي وسيلة من الوسائل."
      },
      {
        "number": 37,
        "question": "ما حكم الإجهاض دون ضرورة؟",
        "choices": [
          "مباح",
          "مكروه",
          "محرم",
          "واجب"
        ],
        "correct_symbol": "ج",
        "correct_answer": "محرم",
        "page": "144",
        "source_text": "أفتى العلماء بحرمة الاعتداء على الجنين وإسقاطه؛ لعموم النهي عن الاعتداء على النفس التي حرم الله تعالى قتلها إلا بالحق."
      },
      {
        "number": 38,
        "question": "ما الدليل الشرعي على حرمة الإجهاض دون ضرورة؟",
        "choices": [
          "قوله تعالى: ﴿وَلَا تَقْتُلُوا أَوْلَادَكُمْ خَشْيَةَ إِمْلَاقٍ﴾",
          "قوله تعالى: ﴿وَلَا تَقْتُلُوا النَّفْسَ الَّتِي حَرَّمَ اللَّهُ إِلَّا بِالْحَقِّ﴾",
          "قوله تعالى: ﴿وَأَحَلَّ اللَّهُ الْبَيْعَ وَحَرَّمَ الرِّبَا﴾",
          "قوله تعالى: ﴿وَأَقِيمُوا الصَّلَاةَ وَآتُوا الزَّكَاةَ﴾"
        ],
        "correct_symbol": "ب",
        "correct_answer": "قوله تعالى: ﴿وَلَا تَقْتُلُوا النَّفْسَ الَّتِي حَرَّمَ اللَّهُ إِلَّا بِالْحَقِّ﴾",
        "page": "144",
        "source_text": "أفتى العلماء بحرمة الاعتداء على الجنين وإسقاطه؛ لعموم النهي عن الاعتداء على النفس التي حرم الله تعالى قتلها إلا بالحق، قال تعالى: ﴿وَلَا تَقْتُلُوا النَّفْسَ الَّتِي حَرَّمَ اللَّهُ إِلَّا بِالْحَقِّ﴾ [الإسراء: ٣٣]."
      },
      {
        "number": 39,
        "question": "متى يجوز الإجهاض؟",
        "choices": [
          "إذا رغبت الأم بذلك",
          "إذا كان بقاء الحمل مهددًا لحياة الأم",
          "إذا كان الجنين مشوهًا",
          "إذا كان هناك عدد كبير من الأطفال"
        ],
        "correct_symbol": "ب",
        "correct_answer": "إذا كان بقاء الحمل مهددًا لحياة الأم",
        "page": "144",
        "source_text": "أما إذا كان بقاء الحمل مهددًا لحياة الأم فيفتى بجواز الإجهاض في هذه الحالة؛ إنقاذًا لحياتها بقرار طبي."
      },
      {
        "number": 40,
        "question": "ما الشرط الأساسي لجواز الإجهاض إذا كان بقاء الحمل مهددًا لحياة الأم؟",
        "choices": [
          "موافقة الزوج",
          "قرار طبي",
          "موافقة الأهل",
          "موافقة الأم فقط"
        ],
        "correct_symbol": "ب",
        "correct_answer": "قرار طبي",
        "page": "144",
        "source_text": "أما إذا كان بقاء الحمل مهددًا لحياة الأم فيفتى بجواز الإجهاض في هذه الحالة؛ إنقاذًا لحياتها بقرار طبي."
      },
      {
        "number": 41,
        "question": "ما القيمة المستفادة من الدرس التي تدعو إلى تقدير قيمة النفس البشرية؟",
        "choices": [
          "السعي إلى الثراء",
          "السعي إلى الشهرة",
          "السعي إلى المحافظة عليها",
          "السعي إلى القوة"
        ],
        "correct_symbol": "ج",
        "correct_answer": "السعي إلى المحافظة عليها",
        "page": "144",
        "source_text": "من القيم المستفادة: أقدر قيمة النفس البشرية، وأسعى إلى المحافظة عليها."
      },
      {
        "number": 42,
        "question": "يُعد حفظ النسل أحد المقاصد الشرعية الكبرى للإسلام، هذه العبارة:",
        "choices": [
          "صحيحة",
          "غير صحيحة",
          "غير واضحة",
          "غير مكتملة"
        ],
        "correct_symbol": "أ",
        "correct_answer": "صحيحة",
        "page": "145",
        "source_text": "يُعد حفظ النسل أحد المقاصد الشرعية الكبرى للإسلام. (عبارة صحيحة)."
      },
      {
        "number": 43,
        "question": "يباح تنظيم النسل بأي وسيلة ممكنة، هذه العبارة:",
        "choices": [
          "صحيحة",
          "غير صحيحة",
          "غير واضحة",
          "غير مكتملة"
        ],
        "correct_symbol": "ب",
        "correct_answer": "غير صحيحة",
        "page": "145",
        "source_text": "يباح تنظيم النسل بأي وسيلة ممكنة. (عبارة غير صحيحة، لأن الوسيلة يجب أن تكون مشروعة ومأمونة الضرر)."
      },
      {
        "number": 44,
        "question": "وجود مرض ضار أو معدٍ يرجى شفاؤه في الزوجين من مسوغات التحديد الدائم للنسل، هذه العبارة:",
        "choices": [
          "صحيحة",
          "غير صحيحة",
          "غير واضحة",
          "غير مكتملة"
        ],
        "correct_symbol": "ب",
        "correct_answer": "غير صحيحة",
        "page": "145",
        "source_text": "وجود مرض ضار أو معدٍ يرجى شفاؤه في الزوجين من مسوغات التحديد الدائم للنسل. (عبارة غير صحيحة، بل هو من مسوغات تنظيم النسل وتأخيره)."
      },
      {
        "number": 45,
        "question": "إذا خاف الزوجان على مسألة الرزق، فيجوز لهما تحديد النسل، هذه العبارة:",
        "choices": [
          "صحيحة",
          "غير صحيحة",
          "غير واضحة",
          "غير مكتملة"
        ],
        "correct_symbol": "ب",
        "correct_answer": "غير صحيحة",
        "page": "145",
        "source_text": "إذا خاف الزوجان على مسألة الرزق، فيجوز لهما تحديد النسل. (عبارة غير صحيحة، لأن تحديد النسل بسبب الخوف على الرزق محرم)."
      },
      {
        "number": 46,
        "question": "أي من الأمثلة الآتية يعد من الوسائل المحرمة المتعلقة بمنع الحمل؟",
        "choices": [
          "العزل",
          "المباعدة بين مدد الحمل بالوسائل الطبية الحديثة",
          "الإجهاض",
          "استخدام الواقي الذكري"
        ],
        "correct_symbol": "ج",
        "correct_answer": "الإجهاض",
        "page": "145",
        "source_text": "من الأمثلة على إحدى الوسائل المحرمة لتنظيم النسل: الإجهاض. (الإجهاض محرم إلا لضرورة طبية تهدد حياة الأم)."
      },
      {
        "number": 47,
        "question": "أي من الأمثلة الآتية يعد من الوسائل المحرمة لتحديد النسل دون حاجة طبية؟",
        "choices": [
          "استئصال الرحم من غير حاجة طبية",
          "العزل",
          "المباعدة بين مدد الحمل بالوسائل الطبية الحديثة",
          "تأخير الحمل بسبب الدراسة"
        ],
        "correct_symbol": "أ",
        "correct_answer": "استئصال الرحم من غير حاجة طبية",
        "page": "145",
        "source_text": "من الأمثلة على إحدى الوسائل المحرمة لتنظيم النسل: استئصال الرحم من غير حاجة طبية. (استئصال الرحم من غير حاجة طبية هو تحديد للنسل وهو محرم)."
      },
      {
        "number": 48,
        "question": "يندرج حكم جواز أكل الميتة في حال الجوع الشديد ضمن قاعدة:",
        "choices": [
          "العادة محكمة",
          "الضرورات تبيح المحظورات",
          "المشقة تجلب التيسير",
          "المعروف عرفًا كالمشروط شرطًا"
        ],
        "correct_symbol": "ب",
        "correct_answer": "الضرورات تبيح المحظورات",
        "page": "145",
        "source_text": "يندرج حكم جواز أكل الميتة في حال الجوع الشديد ضمن قاعدة: الضرورات تبيح المحظورات."
      },
      {
        "number": 49,
        "question": "من أهم مقاصد الزواج التي اعتنى بها الإسلام:",
        "choices": [
          "المال",
          "النسل",
          "العمل",
          "العلم"
        ],
        "correct_symbol": "ب",
        "correct_answer": "النسل",
        "page": "141",
        "source_text": "اعتنى الإسلام بالنسل الذي هو من أهم مقاصد الزواج."
      },
      {
        "number": 50,
        "question": "ما الذي حرمه الإسلام ورتب عليه العقاب في الدنيا والوعيد في الآخرة؟",
        "choices": [
          "قتل النفس أو الإضرار بها",
          "عدم الزواج",
          "عدم الإنجاب",
          "عدم العمل"
        ],
        "correct_symbol": "أ",
        "correct_answer": "قتل النفس أو الإضرار بها",
        "page": "141",
        "source_text": "حرم الإسلام قتل النفس، أو الإضرار بها بأي صورة من الصور، ورتب على ذلك العقاب في الدنيا، والوعيد في الآخرة."
      },
      {
        "number": 51,
        "question": "ما الذي يدل عليه قول النبي صلى الله عليه وسلم: «تَزَوَّجوا الْوَدودَ الْوَلودَ؛ فَإِنِّي مُكاثِرٌ بِكُمُ الْأُمَمَ» [رواه أبو داود]؟",
        "choices": [
          "الدعوة إلى الزهد في الزواج",
          "الدعوة إلى تكثير النسل",
          "الدعوة إلى تنظيم النسل",
          "الدعوة إلى تحديد النسل"
        ],
        "correct_symbol": "ب",
        "correct_answer": "الدعوة إلى تكثير النسل",
        "page": "142",
        "source_text": "قول رسول الله صلى الله عليه وسلم: «تَزَوَّجوا الْوَدودَ الْوَلودَ؛ فَإِنِّي مُكاثِرٌ بِكُمُ الْأُمَمَ» [رواه أبو داود] يدل على الدعوة النبوية إلى تكثير النسل."
      },
      {
        "number": 52,
        "question": "كيف يتوافق تنظيم النسل مع الدعوة النبوية إلى تكثير النسل؟",
        "choices": [
          "لا يتوافقان أبدًا",
          "يتوافقان لأن تنظيم النسل يهدف إلى الحفاظ على جودة النسل وصحته",
          "يتوافقان لأن تنظيم النسل يؤدي إلى زيادة النسل",
          "يتوافقان فقط في حالات الضرورة القصوى"
        ],
        "correct_symbol": "ب",
        "correct_answer": "يتوافقان لأن تنظيم النسل يهدف إلى الحفاظ على جودة النسل وصحته",
        "page": "142",
        "source_text": "أناقش أفراد مجموعتي في العبارة الآتية: «تنظيم النسل لا يتعارض مع الدعوة النبوية إلى تكثير النسل في قول رسول الله صلى الله عليه وسلم: «تَزَوَّجوا الْوَدودَ الْوَلودَ؛ فَإِنِّي مُكاثِرٌ بِكُمُ الْأُمَمَ» [رواه أبو داود]». (التوافق يكمن في أن تنظيم النسل يهدف إلى جودة النسل وصحته وقدرة الأبوين على تربيته، مما يحقق الكثرة المباركة)."
      },
      {
        "number": 53,
        "question": "ما نوع المرض الذي يبرر تأخير الحمل لحين العلاج ضمن أسباب تنظيم النسل؟",
        "choices": [
          "مرض مزمن لا يرجى شفاؤه",
          "مرض نفسي فقط",
          "مرض ضار أو معدٍ يرجى شفاؤه",
          "مرض وراثي غير قابل للعلاج"
        ],
        "correct_symbol": "ج",
        "correct_answer": "مرض ضار أو معدٍ يرجى شفاؤه",
        "page": "142",
        "source_text": "من أسباب إباحة تنظيم النسل: وجود مرض ضار أو معدٍ في الزوجين أو في أحدهما، يرجى شفاؤه، وقد ينتقل إلى أولادهما، فينصح بتأخير الحمل لحين العلاج."
      },
      {
        "number": 54,
        "question": "ما الذي يعارضه تحديد النسل إذا كان لداعي الخوف على الرزق؟",
        "choices": [
          "حكمة التشريع الإسلامي",
          "العقيدة الإسلامية",
          "مصلحة الأولاد",
          "مصلحة الزوجين"
        ],
        "correct_symbol": "ب",
        "correct_answer": "العقيدة الإسلامية",
        "page": "143",
        "source_text": "يعد تحديد النسل بهذا الوصف أمرًا محرمًا، استنادًا إلى الدليلين الآتيين: معارضته العقيدة الإسلامية أن الله إذا كان ذلك لداعي الخوف على الرزق؛ فقد بينت النصوص الشرعية أن الله تعالى تكفل برزق الأبناء والآباء."
      },
      {
        "number": 55,
        "question": "ما الذي تكفل الله به كما بينت النصوص الشرعية إذا كان تحديد النسل لداعي الخوف على الرزق؟",
        "choices": [
          "رزق الأبناء فقط",
          "رزق الآباء فقط",
          "رزق الأبناء والآباء",
          "رزق الأمهات فقط"
        ],
        "correct_symbol": "ج",
        "correct_answer": "رزق الأبناء والآباء",
        "page": "143",
        "source_text": "فقد بينت النصوص الشرعية أن الله تعالى تكفل برزق الأبناء والآباء، قال تعالى: ﴿وَلَا تَقْتُلُوا أَوْلَادَكُمْ خَشْيَةَ إِمْلَاقٍ ۖ نَّحْنُ نَرْزُقُهُمْ وَإِيَّاكُمْ ۚ إِنَّ قَتْلَهُمْ كَانَ خِطْئًا كَبِيرًا﴾."
      },
      {
        "number": 56,
        "question": "من الأمثلة على الضرورة التي تبيح تحديد النسل، الخوف المؤكد على حياة الأم بسبب الحمل، بشرط:",
        "choices": [
          "موافقة الزوج",
          "استشارة الطبيب الثقة المؤتمن",
          "موافقة الأهل",
          "موافقة الأم فقط"
        ],
        "correct_symbol": "ب",
        "correct_answer": "استشارة الطبيب الثقة المؤتمن",
        "page": "143",
        "source_text": "ومن الأمثلة على ذلك: الخوف المؤكد على حياة الأم بسبب الحمل؛ بشرط أن يكون ذلك بعد استشارة الطبيب الثقة المؤتمن."
      },
      {
        "number": 57,
        "question": "ما حكم استئصال رحم المرأة من غير ضرورة طبية؟",
        "choices": [
          "مباح",
          "مكروه",
          "محرم",
          "واجب"
        ],
        "correct_symbol": "ج",
        "correct_answer": "محرم",
        "page": "143",
        "source_text": "تحديد النسل: هو اتخاذ الإجراءات التي تمنع الحمل بصفة دائمة، مثل: استئصال رحم المرأة؛ سواء أكان ذلك بعد إنجاب عدد من الأولاد، أم ابتداء من غير ضرورة طبية. ويعد تحديد النسل بهذا الوصف أمرًا محرمًا."
      },
      {
        "number": 58,
        "question": "ما حكم امتناع المرأة عن الإنجاب حتى تكمل دراستها؟",
        "choices": [
          "مباح",
          "محرم",
          "مكروه",
          "واجب"
        ],
        "correct_symbol": "أ",
        "correct_answer": "مباح",
        "page": "143",
        "source_text": "امتناع المرأة عن الإنجاب حتى تكمل دراستها يصنف تنظيمًا للنسل. وتنظيم النسل مباح عند توافر أسبابه."
      },
      {
        "number": 59,
        "question": "ما حكم تشريع قانون ملزم للأسر بالتوقف عن الإنجاب بعد عدد معين من الأطفال؟",
        "choices": [
          "مباح",
          "محرم",
          "مكروه",
          "واجب"
        ],
        "correct_symbol": "ب",
        "correct_answer": "محرم",
        "page": "143",
        "source_text": "تشريع قانون ملزم للأسر بالتوقف عن الإنجاب بعد عدد معين من الأطفال يصنف تحديدًا للنسل. ويعد تحديد النسل بهذا الوصف أمرًا محرمًا."
      },
      {
        "number": 60,
        "question": "ما حكم عدم حمل الزوجة حتى تشفى من مرضها؟",
        "choices": [
          "مباح",
          "محرم",
          "مكروه",
          "واجب"
        ],
        "correct_symbol": "أ",
        "correct_answer": "مباح",
        "page": "143",
        "source_text": "عدم حمل الزوجة حتى تشفى من مرضها يصنف تنظيمًا للنسل. وتنظيم النسل مباح عند توافر أسبابه، ومنها وجود مرض ضار أو معدٍ يرجى شفاؤه."
      },
      {
        "number": 61,
        "question": "ما الذي أفتى العلماء بحرمته لعموم النهي عن الاعتداء على النفس؟",
        "choices": [
          "تنظيم النسل",
          "تحديد النسل بضرورة",
          "الإجهاض دون ضرورة",
          "العزل"
        ],
        "correct_symbol": "ج",
        "correct_answer": "الإجهاض دون ضرورة",
        "page": "144",
        "source_text": "أفتى العلماء بحرمة الاعتداء على الجنين وإسقاطه؛ لعموم النهي عن الاعتداء على النفس التي حرم الله تعالى قتلها إلا بالحق."
      }
    ]