[
  {
    "number": 1,
    "topic": "التحقق من حل المعادلة التفاضلية",
    "question": "أي من الاقترانات التالية يمثل حلاً للمعادلة التفاضلية \\( y' - 2xy = 0 \\)",
    "choices": [
      "\\( y = e^{x^2} \\)",
      "\\( y = x^2 \\)",
      "\\( y = e^{2x} \\)",
      "\\( y = \\ln(x^2) \\)"
    ],
    "correct_answer": "a",
    "final_answer_text": "\\( y = e^{x^2} \\)",
    "explanation": "باشتقاق \\( y = e^{x^2} \\) نجد أن \\( y' = 2xe^{x^2} \\). بالتعويض في الطرف الأيسر للمعادلة: \\( 2xe^{x^2} - 2x(e^{x^2}) = 0 \\) وهي محققة"
  },
  {
    "number": 2,
    "topic": "التحقق من حل المعادلة التفاضلية",
    "question": "أي من الاقترانات التالية يمثل حلاً للمعادلة التفاضلية \\( y'' + y = 0 \\)",
    "choices": [
      "\\( y = x^2 \\)",
      "\\( y = e^x \\)",
      "\\( y = \\cos x \\)",
      "\\( y = \\ln x \\)"
    ],
    "correct_answer": "c",
    "final_answer_text": "\\( y = \\cos x \\)",
    "explanation": "باشتقاق \\( y = \\cos x \\) مرتين نجد أن \\( y' = -\\sin x \\) و \\( y'' = -\\cos x \\). بالتعويض في المعادلة: \\( -\\cos x + \\cos x = 0 \\) وهي محققة"
  },
  {
    "number": 3,
    "topic": "الحل العام بالتكامل المباشر",
    "question": "الحل العام للمعادلة التفاضلية \\( \\frac{dy}{dx} = \\frac{x}{(x^2+1)^2} \\) هو",
    "choices": [
      "\\( y = -\\frac{1}{2(x^2+1)} + C \\)",
      "\\( y = \\frac{2x}{(x^2+1)^3} + C \\)",
      "\\( y = \\frac{1}{2(x^2+1)} + C \\)",
      "\\( y = \\ln(x^2+1) + C \\)"
    ],
    "correct_answer": "a",
    "final_answer_text": "\\( y = -\\frac{1}{2(x^2+1)} + C \\)",
    "explanation": "باستخدام التعويض \\( u = x^2+1 \\) نجد أن \\( du=2x \\, dx \\). التكامل يصبح \\( \\frac{1}{2} \\int u^{-2} \\, du = -\\frac{1}{2u} + C \\) وبالتعويض نصل للحل النهائي"
  },
  {
    "number": 4,
    "topic": "فصل المتغيرات - معادلة مثلثية",
    "question": "الحل العام للمعادلة التفاضلية \\( \\frac{dy}{dx} = \\cos x \\sin y \\) هو",
    "choices": [
      "\\( \\ln|\\csc y - \\cot y| = \\sin x + C \\)",
      "\\( -\\ln|\\csc y + \\cot y| = \\sin x + C \\)",
      "\\( \\ln|\\tan(y/2)| = \\sin x + C \\)",
      "\\( \\cos y = -\\sin x + C \\)"
    ],
    "correct_answer": "c",
    "final_answer_text": "\\( \\ln|\\tan(y/2)| = \\sin x + C \\)",
    "explanation": "بفصل المتغيرات والمكاملة: \\( \\int \\csc y \\, dy = \\int \\cos x \\, dx \\). تكامل قاطع التمام هو \\( \\ln|\\tan(y/2)| \\) وتكامل الجتا هو الجيب"
  },
  {
    "number": 5,
    "topic": "فصل المتغيرات - الصورة الجبرية",
    "question": "عند فصل متغيرات المعادلة \\( (2x+1)(x+2)\\frac{dy}{dx} = -3(y-2) \\)، الصورة الصحيحة للخطوة الأولى هي",
    "choices": [
      "\\( \\ln|y-2| = -3\\int\\frac{dx}{(2x+1)(x+2)} + C \\)",
      "\\( \\ln|y-2| = -\\ln|(2x+1)(x+2)| + C \\)",
      "\\( y - 2 = K(2x+1)(x+2) \\)",
      "\\( \\ln|y-2| = \\ln|(2x+1)(x+2)| + C \\)"
    ],
    "correct_answer": "a",
    "final_answer_text": "\\( \\ln|y-2| = -3\\int\\frac{dx}{(2x+1)(x+2)} + C \\)",
    "explanation": "بقسمة الطرفين على \\( (y-2) \\) و \\( (2x+1)(x+2) \\) نصل لهذه الصورة التكاملية الصحيحة لعزل المتغيرات"
  },
  {
    "number": 6,
    "topic": "الحل الخاص للمعادلة",
    "question": "الحل الخاص للمعادلة \\( \\frac{dy}{dx} = 2\\cos^2 x \\cos^2 y \\) مع الشرط \\( y(0) = \\frac{\\pi}{4} \\) هو",
    "choices": [
      "\\( \\tan y = \\sin x \\cos x + x + 1 \\)",
      "\\( \\tan y = x + \\sin x \\cos x + 1 \\)",
      "\\( \\tan y = 2x + 1 \\)",
      "\\( \\sec^2 y = 2\\cos^2 x + C \\)"
    ],
    "correct_answer": "b",
    "final_answer_text": "\\( \\tan y = x + \\sin x \\cos x + 1 \\)",
    "explanation": "بفصل المتغيرات نكامل \\( \\int \\sec^2 y \\, dy = \\int (1 + \\cos 2x) \\, dx \\). بالتعويض نجد \\( C=1 \\) وباستخدام متطابقة ضعف الزاوية يظهر الحل النهائي"
  },
  {
    "number": 7,
    "topic": "قاعدة العلاقة من ميل المماس",
    "question": "إذا كان ميل المماس لمنحنى هو \\( \\frac{dy}{dx} = y\\cos x \\) ويمر بالنقطة \\( (0,1) \\)، فإن قاعدة العلاقة هي",
    "choices": [
      "\\( y = e^{\\sin x} \\)",
      "\\( y = e^{\\sin x - 1} \\)",
      "\\( y = \\sin x + 1 \\)",
      "\\( y = e^x\\cos x \\)"
    ],
    "correct_answer": "a",
    "final_answer_text": "\\( y = e^{\\sin x} \\)",
    "explanation": "بالفصل والمكاملة نجد \\( \\ln|y| = \\sin x + C \\). بتعويض النقطة نجد أن \\( C=0 \\)، وبالتحويل للصورة الأسية نحصل على القاعدة المطلوبة"
  },
  {
    "number": 8,
    "topic": "تطبيق درجة الحرارة",
    "question": "تتبع درجة حرارة سائل العلاقة \\( \\frac{dA}{dt} = 2(A-20) \\) مع \\( A(0)=5 \\). الزمن المستغرق لتصل الحرارة إلى 18 درجة هو",
    "choices": [
      "\\( t = \\frac{\\ln(2/15)}{2} \\)",
      "\\( t = 1.00 \\text{ h} \\)",
      "\\( t = 0.5 \\text{ h} \\)",
      "\\( t = 3 \\text{ h} \\)"
    ],
    "correct_answer": "a",
    "final_answer_text": "\\( t = \\frac{\\ln(2/15)}{2} \\)",
    "explanation": "بالتكامل نجد \\( A = 20 - 15e^{2t} \\). عند تعويض \\( A=18 \\) وحل المعادلة الأسية يظهر الزمن بدلالة اللوغاريتم كما في الخيار الأول"
  },
  {
    "number": 9,
    "topic": "نموذج النمو الأسي",
    "question": "إذا كان مجتمع ينمو حسب \\( \\frac{dP}{dt} = kP \\) وبدأ بـ \\( P_0 \\)، فما هو الحل العام؟",
    "choices": [
      "\\( P = P_0 e^{kt} \\)",
      "\\( P = kt + P_0 \\)",
      "\\( \\ln P = k + C \\)",
      "\\( P = e^{kt} + C \\)"
    ],
    "correct_answer": "a",
    "final_answer_text": "\\( P = P_0 e^{kt} \\)",
    "explanation": "بفصل المتغيرات والمكاملة نصل للصورة اللوغاريتمية التي تتحول لنمو أسي باستخدام القيمة الابتدائية كمعامل للقوة"
  },
  {
    "number": 10,
    "topic": "تطبيق انتشار الأمراض",
    "question": "في نموذج انتشار مرض، إذا كان الحل هو \\( \\ln|\\frac{s}{1050-s}| = 0.21t-3 \\)، فما قيمة t عندما \\( s=800 \\)؟",
    "choices": [
      "\\( t \\approx 20 \\text{ days} \\)",
      "\\( t \\approx 11 \\text{ days} \\)",
      "\\( t \\approx 14 \\text{ days} \\)",
      "\\( t \\approx 5 \\text{ days} \\)"
    ],
    "correct_answer": "a",
    "final_answer_text": "\\( t \\approx 20 \\text{ days} \\)",
    "explanation": "بالتعويض: \\( \\ln(800/250) = 0.21t-3 \\). القيمة اللوغاريتمية مضافاً إليها 3 ثم مقسومة على معامل الزمن تعطي تقريباً 20 يوماً"
  }
]